{
  "overall_accuracy": 0.8402,
  "macro_f1": 0.8399,
  "weighted_f1": 0.8399,
  "per_class": {
    "airplane": {
      "precision": 0.8913,
      "recall": 0.82,
      "f1": 0.8542,
      "support": 100
    },
    "airport": {
      "precision": 0.8095,
      "recall": 0.68,
      "f1": 0.7391,
      "support": 100
    },
    "baseball diamond": {
      "precision": 0.8037,
      "recall": 0.86,
      "f1": 0.8309,
      "support": 100
    },
    "basketball court": {
      "precision": 0.7473,
      "recall": 0.68,
      "f1": 0.712,
      "support": 100
    },
    "beach": {
      "precision": 0.9231,
      "recall": 0.96,
      "f1": 0.9412,
      "support": 100
    },
    "bridge": {
      "precision": 0.9359,
      "recall": 0.73,
      "f1": 0.8202,
      "support": 100
    },
    "chaparral": {
      "precision": 0.9604,
      "recall": 0.97,
      "f1": 0.9652,
      "support": 100
    },
    "church": {
      "precision": 0.7647,
      "recall": 0.78,
      "f1": 0.7723,
      "support": 100
    },
    "circular farmland": {
      "precision": 0.8932,
      "recall": 0.92,
      "f1": 0.9064,
      "support": 100
    },
    "cloud": {
      "precision": 0.97,
      "recall": 0.97,
      "f1": 0.97,
      "support": 100
    },
    "commercial area": {
      "precision": 0.8351,
      "recall": 0.81,
      "f1": 0.8223,
      "support": 100
    },
    "dense residential": {
      "precision": 0.7712,
      "recall": 0.91,
      "f1": 0.8349,
      "support": 100
    },
    "desert": {
      "precision": 0.9038,
      "recall": 0.94,
      "f1": 0.9216,
      "support": 100
    },
    "forest": {
      "precision": 0.9381,
      "recall": 0.91,
      "f1": 0.9239,
      "support": 100
    },
    "freeway": {
      "precision": 0.8687,
      "recall": 0.86,
      "f1": 0.8643,
      "support": 100
    },
    "golf course": {
      "precision": 0.8727,
      "recall": 0.96,
      "f1": 0.9143,
      "support": 100
    },
    "ground track field": {
      "precision": 0.8,
      "recall": 0.76,
      "f1": 0.7795,
      "support": 100
    },
    "harbor": {
      "precision": 0.8879,
      "recall": 0.95,
      "f1": 0.9179,
      "support": 100
    },
    "industrial area": {
      "precision": 0.7579,
      "recall": 0.72,
      "f1": 0.7385,
      "support": 100
    },
    "intersection": {
      "precision": 0.7573,
      "recall": 0.78,
      "f1": 0.7685,
      "support": 100
    },
    "island": {
      "precision": 0.9029,
      "recall": 0.93,
      "f1": 0.9163,
      "support": 100
    },
    "lake": {
      "precision": 0.8737,
      "recall": 0.83,
      "f1": 0.8513,
      "support": 100
    },
    "meadow": {
      "precision": 0.9651,
      "recall": 0.83,
      "f1": 0.8925,
      "support": 100
    },
    "medium residential": {
      "precision": 0.6942,
      "recall": 0.84,
      "f1": 0.7602,
      "support": 100
    },
    "mobile home park": {
      "precision": 0.8952,
      "recall": 0.94,
      "f1": 0.9171,
      "support": 100
    },
    "mountain": {
      "precision": 0.8878,
      "recall": 0.87,
      "f1": 0.8788,
      "support": 100
    },
    "overpass": {
      "precision": 0.8614,
      "recall": 0.87,
      "f1": 0.8657,
      "support": 100
    },
    "palace": {
      "precision": 0.6486,
      "recall": 0.72,
      "f1": 0.6825,
      "support": 100
    },
    "parking lot": {
      "precision": 0.8519,
      "recall": 0.92,
      "f1": 0.8846,
      "support": 100
    },
    "railway": {
      "precision": 0.8587,
      "recall": 0.79,
      "f1": 0.8229,
      "support": 100
    },
    "railway station": {
      "precision": 0.6632,
      "recall": 0.63,
      "f1": 0.6462,
      "support": 100
    },
    "rectangular farmland": {
      "precision": 0.7736,
      "recall": 0.82,
      "f1": 0.7961,
      "support": 100
    },
    "river": {
      "precision": 0.8152,
      "recall": 0.75,
      "f1": 0.7812,
      "support": 100
    },
    "roundabout": {
      "precision": 0.7374,
      "recall": 0.73,
      "f1": 0.7337,
      "support": 100
    },
    "runway": {
      "precision": 0.9263,
      "recall": 0.88,
      "f1": 0.9026,
      "support": 100
    },
    "sea ice": {
      "precision": 1.0,
      "recall": 0.97,
      "f1": 0.9848,
      "support": 100
    },
    "ship": {
      "precision": 0.8737,
      "recall": 0.83,
      "f1": 0.8513,
      "support": 100
    },
    "snowberg": {
      "precision": 0.9167,
      "recall": 0.99,
      "f1": 0.9519,
      "support": 100
    },
    "sparse residential": {
      "precision": 0.8163,
      "recall": 0.8,
      "f1": 0.8081,
      "support": 100
    },
    "stadium": {
      "precision": 0.713,
      "recall": 0.77,
      "f1": 0.7404,
      "support": 100
    },
    "storage tank": {
      "precision": 0.7315,
      "recall": 0.79,
      "f1": 0.7596,
      "support": 100
    },
    "tennis court": {
      "precision": 0.8488,
      "recall": 0.73,
      "f1": 0.7849,
      "support": 100
    },
    "terrace": {
      "precision": 0.9082,
      "recall": 0.89,
      "f1": 0.899,
      "support": 100
    },
    "thermal power station": {
      "precision": 0.7672,
      "recall": 0.89,
      "f1": 0.8241,
      "support": 100
    },
    "wetland": {
      "precision": 0.9022,
      "recall": 0.83,
      "f1": 0.8646,
      "support": 100
    }
  }
}